setup.py
LDB_Algebra.egg-info/PKG-INFO
LDB_Algebra.egg-info/SOURCES.txt
LDB_Algebra.egg-info/dependency_links.txt
LDB_Algebra.egg-info/namespace_packages.txt
LDB_Algebra.egg-info/requires.txt
LDB_Algebra.egg-info/top_level.txt
ldb/__init__.py
ldb/algebra/__init__.py
ldb/algebra/distribute.py
ldb/algebra/expression.py
ldb/algebra/function.py
ldb/algebra/implicit_differentiation.py
ldb/algebra/manager.py
ldb/algebra/math.py
ldb/algebra/power.py
ldb/algebra/statistics.py
ldb/algebra/trig.py