Metadata-Version: 1.0
Name: LDB-Algebra
Version: 0.3.2
Summary: An algebra/calculus package for the LDB framework
Home-page: http://www.eldebe.org/ldb/algebra/
Author: Alex Orange
Author-email: alex@eldebe.org
License: AGPLv3
Platform: UNKNOWN
